{"Jun Seok Kang": [0.9901176691055298, ["PoMo: Generating Entity-Specific Post-Modifiers in Context", ["Jun Seok Kang", "Robert L. Logan IV", "Zewei Chu", "Yang Chen", "Dheeru Dua", "Kevin Gimpel", "Sameer Singh", "Niranjan Balasubramanian"], "https://aclweb.org/anthology/papers/N/N19/N19-1089/", 13, "naacl", 2019]], "Sungjoon Park": [0.9976610243320465, ["Conversation Model Fine-Tuning for Classifying Client Utterances in Counseling Dialogues", ["Sungjoon Park", "Donghyun Kim", "Alice H. Oh"], "https://aclweb.org/anthology/papers/N/N19/N19-1148/", 12, "naacl", 2019]], "Heeyoung Kwon": [0.9977992027997971, ["Repurposing Entailment for Multi-Hop Question Answering Tasks", ["Harsh Trivedi", "Heeyoung Kwon", "Tushar Khot", "Ashish Sabharwal", "Niranjan Balasubramanian"], "https://aclweb.org/anthology/papers/N/N19/N19-1302/", 11, "naacl", 2019]], "Gunhee Kim": [1, ["AudioCaps: Generating Captions for Audios in The Wild", ["Chris Dongjoo Kim", "Byeongchang Kim", "Hyunmin Lee", "Gunhee Kim"], "https://aclweb.org/anthology/papers/N/N19/N19-1011/", 14, "naacl", 2019], ["Abstractive Summarization of Reddit Posts with Multi-level Memory Networks", ["Byeongchang Kim", "Hyunwoo Kim", "Gunhee Kim"], "https://aclweb.org/anthology/papers/N/N19/N19-1260/", 13, "naacl", 2019]], "Geewook Kim": [0.9997565448284149, ["Segmentation-free compositional n-gram embedding", ["Geewook Kim", "Kazuki Fukui", "Hidetoshi Shimodaira"], "https://aclweb.org/anthology/papers/N/N19/N19-1324/", 9, "naacl", 2019]], "Eunsol Choi": [0.9460698068141937, ["No Permanent Friends or Enemies: Tracking Relationships between Nations from News", ["Xiaochuang Han", "Eunsol Choi", "Chenhao Tan"], "https://aclweb.org/anthology/papers/N/N19/N19-1167/", 17, "naacl", 2019], ["pair2vec: Compositional Word-Pair Embeddings for Cross-Sentence Inference", ["Mandar Joshi", "Eunsol Choi", "Omer Levy", "Daniel S. Weld", "Luke Zettlemoyer"], "https://aclweb.org/anthology/papers/N/N19/N19-1362/", 12, "naacl", 2019]], "Donghyun Kim": [0.9940284192562103, ["Conversation Model Fine-Tuning for Classifying Client Utterances in Counseling Dialogues", ["Sungjoon Park", "Donghyun Kim", "Alice H. Oh"], "https://aclweb.org/anthology/papers/N/N19/N19-1148/", 12, "naacl", 2019]], "Hyunmin Lee": [0.9861587285995483, ["AudioCaps: Generating Captions for Audios in The Wild", ["Chris Dongjoo Kim", "Byeongchang Kim", "Hyunmin Lee", "Gunhee Kim"], "https://aclweb.org/anthology/papers/N/N19/N19-1011/", 14, "naacl", 2019]], "Yoon Kim": [0.7215062379837036, ["Unsupervised Recurrent Neural Network Grammars", ["Yoon Kim", "Alexander M. Rush", "Lei Yu", "Adhiguna Kuncoro", "Chris Dyer", "Gabor Melis"], "https://aclweb.org/anthology/papers/N/N19/N19-1114/", 13, "naacl", 2019]], "Jong-Hyeok Lee": [0.9997644126415253, ["Decay-Function-Free Time-Aware Attention to Context and Speaker Indicator for Spoken Language Understanding", ["Jonggu Kim", "Jong-Hyeok Lee"], "https://aclweb.org/anthology/papers/N/N19/N19-1372/", 9, "naacl", 2019]], "Tagyoung Chung": [0.9779298901557922, ["Simple Question Answering with Subgraph Ranking and Joint-Scoring", ["Wenbo Zhao", "Tagyoung Chung", "Anuj Kumar Goyal", "Angeliki Metallinou"], "https://aclweb.org/anthology/papers/N/N19/N19-1029/", 11, "naacl", 2019], ["Practical Semantic Parsing for Spoken Language Understanding", ["Marco Damonte", "Rahul Goel", "Tagyoung Chung"], "https://aclweb.org/anthology/papers/N/N19/N19-2003/", 8, "naacl", 2019]], "SangKeun Lee": [1, ["Adaptive Convolution for Text Classification", ["Byung-Ju Choi", "Jun-Hyung Park", "SangKeun Lee"], "https://aclweb.org/anthology/papers/N/N19/N19-1256/", 11, "naacl", 2019]], "Yejin Huh": [0.6379871666431427, ["Improving Knowledge Base Construction from Robust Infobox Extraction", ["Boya Peng", "Yejin Huh", "Xiao Ling", "Michele Banko"], "https://aclweb.org/anthology/papers/N/N19/N19-2018/", 11, "naacl", 2019]], "Dekun Wu": [0.6502675265073776, ["FreebaseQA: A New Factoid QA Data Set Matching Trivia-Style Question-Answer Pairs with Freebase", ["Kelvin Jiang", "Dekun Wu", "Hui Jiang"], "https://aclweb.org/anthology/papers/N/N19/N19-1028/", 6, "naacl", 2019]], "Yejin Choi": [0.6379871666431427, ["MathQA: Towards Interpretable Math Word Problem Solving with Operation-Based Formalisms", ["Aida Amini", "Saadia Gabriel", "Shanchuan Lin", "Rik Koncel-Kedziorski", "Yejin Choi", "Hannaneh Hajishirzi"], "https://aclweb.org/anthology/papers/N/N19/N19-1245/", 11, "naacl", 2019], ["Benchmarking Hierarchical Script Knowledge", ["Yonatan Bisk", "Jan Buys", "Karl Pichotta", "Yejin Choi"], "https://aclweb.org/anthology/papers/N/N19/N19-1412/", 9, "naacl", 2019]], "Chris Dongjoo Kim": [0.9905963987112045, ["AudioCaps: Generating Captions for Audios in The Wild", ["Chris Dongjoo Kim", "Byeongchang Kim", "Hyunmin Lee", "Gunhee Kim"], "https://aclweb.org/anthology/papers/N/N19/N19-1011/", 14, "naacl", 2019]], "Sungjin Lee": [0.8338425606489182, ["Jointly Optimizing Diversity and Relevance in Neural Response Generation", ["Xiang Gao", "Sungjin Lee", "Yizhe Zhang", "Chris Brockett", "Michel Galley", "Jianfeng Gao", "Bill Dolan"], "https://aclweb.org/anthology/papers/N/N19/N19-1125/", 10, "naacl", 2019]], "Young-Bum Kim": [0.9703183174133301, ["Continuous Learning for Large-scale Personalized Domain Classification", ["Han Li", "Jihwan Lee", "Sidharth Mudgal", "Ruhi Sarikaya", "Young-Bum Kim"], "https://aclweb.org/anthology/papers/N/N19/N19-1379/", 11, "naacl", 2019], ["Locale-agnostic Universal Domain Classification Model in Spoken Language Understanding", ["Jihwan Lee", "Ruhi Sarikaya", "Young-Bum Kim"], "https://aclweb.org/anthology/papers/N/N19/N19-2002/", 7, "naacl", 2019]], "Youngja Park": [0.9960693567991257, ["Predicting Malware Attributes from Cybersecurity Texts", ["Arpita Roy", "Youngja Park", "Shimei Pan"], "https://aclweb.org/anthology/papers/N/N19/N19-1293/", 5, "naacl", 2019]], "Jihwan Lee": [0.9722291678190231, ["Continuous Learning for Large-scale Personalized Domain Classification", ["Han Li", "Jihwan Lee", "Sidharth Mudgal", "Ruhi Sarikaya", "Young-Bum Kim"], "https://aclweb.org/anthology/papers/N/N19/N19-1379/", 11, "naacl", 2019], ["Locale-agnostic Universal Domain Classification Model in Spoken Language Understanding", ["Jihwan Lee", "Ruhi Sarikaya", "Young-Bum Kim"], "https://aclweb.org/anthology/papers/N/N19/N19-2002/", 7, "naacl", 2019]], "Jun-Hyung Park": [0.986799418926239, ["Adaptive Convolution for Text Classification", ["Byung-Ju Choi", "Jun-Hyung Park", "SangKeun Lee"], "https://aclweb.org/anthology/papers/N/N19/N19-1256/", 11, "naacl", 2019]], "Suyoun Kim": [0.9995113462209702, ["Acoustic-to-Word Models with Conversational Context Information", ["Suyoun Kim", "Florian Metze"], "https://aclweb.org/anthology/papers/N/N19/N19-1283/", 6, "naacl", 2019]], "Hyunwoo Kim": [0.9994963705539703, ["Abstractive Summarization of Reddit Posts with Multi-level Memory Networks", ["Byeongchang Kim", "Hyunwoo Kim", "Gunhee Kim"], "https://aclweb.org/anthology/papers/N/N19/N19-1260/", 13, "naacl", 2019]], "Byung-Ju Choi": [0.9922797083854675, ["Adaptive Convolution for Text Classification", ["Byung-Ju Choi", "Jun-Hyung Park", "SangKeun Lee"], "https://aclweb.org/anthology/papers/N/N19/N19-1256/", 11, "naacl", 2019]], "Chuhan Wu": [0.6920769065618515, ["Hierarchical User and Item Representation with Three-Tier Attention for Recommendation", ["Chuhan Wu", "Fangzhao Wu", "Junxin Liu", "Yongfeng Huang"], "https://aclweb.org/anthology/papers/N/N19/N19-1180/", 9, "naacl", 2019]], "Jonggu Kim": [0.9696092754602432, ["Decay-Function-Free Time-Aware Attention to Context and Speaker Indicator for Spoken Language Understanding", ["Jonggu Kim", "Jong-Hyeok Lee"], "https://aclweb.org/anthology/papers/N/N19/N19-1372/", 9, "naacl", 2019]], "Byeongchang Kim": [0.9999296367168427, ["AudioCaps: Generating Captions for Audios in The Wild", ["Chris Dongjoo Kim", "Byeongchang Kim", "Hyunmin Lee", "Gunhee Kim"], "https://aclweb.org/anthology/papers/N/N19/N19-1011/", 14, "naacl", 2019], ["Abstractive Summarization of Reddit Posts with Multi-level Memory Networks", ["Byeongchang Kim", "Hyunwoo Kim", "Gunhee Kim"], "https://aclweb.org/anthology/papers/N/N19/N19-1260/", 13, "naacl", 2019]], "Alice H. Oh": [1, ["Conversation Model Fine-Tuning for Classifying Client Utterances in Counseling Dialogues", ["Sungjoon Park", "Donghyun Kim", "Alice H. Oh"], "https://aclweb.org/anthology/papers/N/N19/N19-1148/", 12, "naacl", 2019]], "Ji-Ung Lee": [0.7448312640190125, ["Text Processing Like Humans Do: Visually Attacking and Shielding NLP Systems", ["Steffen Eger", "Gozde Gul Sahin", "Andreas Ruckle", "Ji-Ung Lee", "Claudia Schulz", "Mohsen Mesgar", "Krishnkant Swarnkar", "Edwin Simpson", "Iryna Gurevych"], "https://aclweb.org/anthology/papers/N/N19/N19-1165/", 14, "naacl", 2019]]}